pyrender/__init__.py
pyrender/camera.py
pyrender/constants.py
pyrender/font.py
pyrender/light.py
pyrender/material.py
pyrender/mesh.py
pyrender/node.py
pyrender/offscreen.py
pyrender/opengl_utils.py
pyrender/primitive.py
pyrender/renderer.py
pyrender/sampler.py
pyrender/scene.py
pyrender/shader_program.py
pyrender/texture.py
pyrender/trackball.py
pyrender/utils.py
pyrender/viewer.py
pyrender/fonts/OpenSans-Bold.ttf
pyrender/fonts/OpenSans-BoldItalic.ttf
pyrender/fonts/OpenSans-ExtraBold.ttf
pyrender/fonts/OpenSans-ExtraBoldItalic.ttf
pyrender/fonts/OpenSans-Italic.ttf
pyrender/fonts/OpenSans-Light.ttf
pyrender/fonts/OpenSans-LightItalic.ttf
pyrender/fonts/OpenSans-Regular.ttf
pyrender/fonts/OpenSans-Semibold.ttf
pyrender/fonts/OpenSans-SemiboldItalic.ttf
pyrender/platforms/__init__.py
pyrender/platforms/base.py
pyrender/platforms/egl.py
pyrender/platforms/osmesa.py
pyrender/platforms/pyglet_platform.py
pyrender/shaders/debug_quad.frag
pyrender/shaders/debug_quad.vert
pyrender/shaders/flat.frag
pyrender/shaders/flat.vert
pyrender/shaders/mesh.frag
pyrender/shaders/mesh.vert
pyrender/shaders/mesh_depth.frag
pyrender/shaders/mesh_depth.vert
pyrender/shaders/segmentation.frag
pyrender/shaders/segmentation.vert
pyrender/shaders/text.frag
pyrender/shaders/text.vert
pyrender/shaders/vertex_normals.frag
pyrender/shaders/vertex_normals.geom
pyrender/shaders/vertex_normals.vert
pyrender/shaders/vertex_normals_pc.geom
scikit_robot_pyrender-0.1.48.dist-info/licenses/LICENSE
scikit_robot_pyrender-0.1.48.dist-info/METADATA
scikit_robot_pyrender-0.1.48.dist-info/WHEEL
scikit_robot_pyrender-0.1.48.dist-info/top_level.txt
scikit_robot_pyrender-0.1.48.dist-info/RECORD
