Metadata-Version: 2.4
Name: scikit-robot-pyrender
Version: 0.1.48
Summary: Easy-to-use Python renderer for 3D visualization
Home-page: https://github.com/iory/scikit-robot-pyrender
Author: Matthew Matl (original), Iori Yanokura (fork)
Author-email: yanokura@jsk.imi.i.u-tokyo.ac.jp
License: MIT License
Keywords: rendering graphics opengl 3d visualization pbr gltf
Classifier: Development Status :: 4 - Beta
Classifier: License :: OSI Approved :: MIT License
Classifier: Operating System :: POSIX :: Linux
Classifier: Operating System :: MacOS :: MacOS X
Classifier: Programming Language :: Python :: 3.8
Classifier: Programming Language :: Python :: 3.9
Classifier: Programming Language :: Python :: 3.10
Classifier: Programming Language :: Python :: 3.11
Classifier: Programming Language :: Python :: 3.12
Classifier: Programming Language :: Python :: 3.13
Classifier: Natural Language :: English
Classifier: Topic :: Scientific/Engineering
License-File: LICENSE
Requires-Dist: freetype-py
Requires-Dist: imageio
Requires-Dist: networkx
Requires-Dist: numpy
Requires-Dist: Pillow
Requires-Dist: pyglet>=1.4.10
Requires-Dist: PyOpenGL~=3.1.0
Requires-Dist: scipy
Requires-Dist: six
Requires-Dist: trimesh
Provides-Extra: dev
Requires-Dist: flake8; extra == "dev"
Requires-Dist: pre-commit; extra == "dev"
Requires-Dist: pytest; extra == "dev"
Requires-Dist: pytest-cov; extra == "dev"
Requires-Dist: tox; extra == "dev"
Provides-Extra: docs
Requires-Dist: sphinx; extra == "docs"
Requires-Dist: sphinx_rtd_theme; extra == "docs"
Requires-Dist: sphinx-automodapi; extra == "docs"
Dynamic: author
Dynamic: author-email
Dynamic: classifier
Dynamic: description
Dynamic: home-page
Dynamic: keywords
Dynamic: license
Dynamic: license-file
Dynamic: provides-extra
Dynamic: requires-dist
Dynamic: summary
